LICENSE
README.md
ignori/__init__.py
ignori/app.py
ignori/ignore_file.py
ignori/screens/__init__.py
ignori/screens/modals/__init__.py
ignori/screens/modals/confirm_modal.py
ignori/screens/modals/info_modal.py
ignori/styles/global.tcss
ignori/styles/modals.tcss
ignori/styles/widgets.tcss
ignori/templates/AL.gitignore
ignori/templates/Actionscript.gitignore
ignori/templates/Ada.gitignore
ignori/templates/Agda.gitignore
ignori/templates/Android.gitignore
ignori/templates/AppEngine.gitignore
ignori/templates/AppceleratorTitanium.gitignore
ignori/templates/ArchLinuxPackages.gitignore
ignori/templates/Autotools.gitignore
ignori/templates/Ballerina.gitignore
ignori/templates/C++.gitignore
ignori/templates/C.gitignore
ignori/templates/CFWheels.gitignore
ignori/templates/CMake.gitignore
ignori/templates/CUDA.gitignore
ignori/templates/CakePHP.gitignore
ignori/templates/ChefCookbook.gitignore
ignori/templates/Clojure.gitignore
ignori/templates/CodeIgniter.gitignore
ignori/templates/CommonLisp.gitignore
ignori/templates/Composer.gitignore
ignori/templates/Concrete5.gitignore
ignori/templates/Coq.gitignore
ignori/templates/CraftCMS.gitignore
ignori/templates/D.gitignore
ignori/templates/DM.gitignore
ignori/templates/Dart.gitignore
ignori/templates/Delphi.gitignore
ignori/templates/Drupal.gitignore
ignori/templates/Eagle.gitignore
ignori/templates/Elisp.gitignore
ignori/templates/Elixir.gitignore
ignori/templates/Elm.gitignore
ignori/templates/Erlang.gitignore
ignori/templates/ExpressionEngine.gitignore
ignori/templates/ExtJs.gitignore
ignori/templates/Fancy.gitignore
ignori/templates/Finale.gitignore
ignori/templates/FlaxEngine.gitignore
ignori/templates/ForceDotCom.gitignore
ignori/templates/Fortran.gitignore
ignori/templates/FuelPHP.gitignore
ignori/templates/GWT.gitignore
ignori/templates/Gcov.gitignore
ignori/templates/GitBook.gitignore
ignori/templates/GitHubPages.gitignore
ignori/templates/Gleam.gitignore
ignori/templates/Go.gitignore
ignori/templates/Godot.gitignore
ignori-1.1.0.dist-info/LICENSE
ignori-1.1.0.dist-info/METADATA
ignori-1.1.0.dist-info/WHEEL
ignori-1.1.0.dist-info/entry_points.txt
ignori-1.1.0.dist-info/RECORD
