Metadata-Version: 2.1
Name: ignori
Version: 1.1.0
Summary: Generate .gitignore file without leaving the terminal.
Home-page: https://github.com/EGAMAGZ/ignori
License: MIT
Keywords: gitignore-generator,generator,ignori,tui,textual,textualize,developer-tool,tool
Author: Gamaliel Garcia
Author-email: 46827955+EGAMAGZ@users.noreply.github.com
Maintainer: Gamaliel Garcia
Maintainer-email: 46827955+EGAMAGZ@users.noreply.github.com
Requires-Python: >=3.11,<4.0.0
Classifier: Development Status :: 5 - Production/Stable
Classifier: Environment :: Console
Classifier: Environment :: Console :: Curses
Classifier: License :: OSI Approved :: MIT License
Classifier: Operating System :: OS Independent
Classifier: Programming Language :: Python :: 3
Classifier: Programming Language :: Python :: 3.11
Classifier: Programming Language :: Python :: 3.12
Classifier: Programming Language :: Python :: 3.13
Classifier: Topic :: Software Development
Classifier: Topic :: Software Development :: Code Generators
Classifier: Topic :: Software Development :: Version Control :: Git
Classifier: Typing :: Typed
Requires-Dist: rich (>=13.7.1,<14.0.0)
Requires-Dist: textual (>=0.73.0,<0.74.0)
Project-URL: Bug Tracker, https://github.com/EGAMAGZ/ignori/issues
Project-URL: Repository, https://github.com/EGAMAGZ/ignori
